odoo/addons/account_payment_order_vendor_email/README.rst
odoo/addons/account_payment_order_vendor_email/__init__.py
odoo/addons/account_payment_order_vendor_email/__manifest__.py
odoo/addons/account_payment_order_vendor_email/data/mail_template.xml
odoo/addons/account_payment_order_vendor_email/i18n/account_payment_order_vendor_email.pot
odoo/addons/account_payment_order_vendor_email/models/__init__.py
odoo/addons/account_payment_order_vendor_email/models/account_payment_mode.py
odoo/addons/account_payment_order_vendor_email/readme/CONTRIBUTORS.rst
odoo/addons/account_payment_order_vendor_email/readme/DESCRIPTION.rst
odoo/addons/account_payment_order_vendor_email/readme/USAGE.rst
odoo/addons/account_payment_order_vendor_email/static/description/icon.png
odoo/addons/account_payment_order_vendor_email/static/description/index.html
odoo/addons/account_payment_order_vendor_email/tests/__init__.py
odoo/addons/account_payment_order_vendor_email/tests/test_account_payment_order_vendor_mail.py
odoo/addons/account_payment_order_vendor_email/views/account_payment_mode_view.xml
odoo/addons/account_payment_order_vendor_email/views/account_payment_order_view.xml
odoo14_addon_account_payment_order_vendor_email-14.0.2.0.0.dist-info/METADATA
odoo14_addon_account_payment_order_vendor_email-14.0.2.0.0.dist-info/WHEEL
odoo14_addon_account_payment_order_vendor_email-14.0.2.0.0.dist-info/top_level.txt
odoo14_addon_account_payment_order_vendor_email-14.0.2.0.0.dist-info/RECORD
