Metadata-Version: 2.1
Name: odoo14-addon-account-payment-order-vendor-email
Version: 14.0.2.0.0
Summary: Account Payment Order Email
Home-page: https://github.com/OCA/bank-payment
Author: Open Source Integrators, Odoo Community Association (OCA)
Author-email: support@odoo-community.org
License: AGPL-3
Platform: UNKNOWN
Classifier: Programming Language :: Python
Classifier: Framework :: Odoo
Classifier: Framework :: Odoo :: 14.0
Classifier: License :: OSI Approved :: GNU Affero General Public License v3
Requires-Python: >=3.6
Requires-Dist: odoo14-addon-account-payment-mode
Requires-Dist: odoo14-addon-account-payment-order
Requires-Dist: odoo (<14.1dev,>=14.0a)
